dspygen/__init__.py
dspygen/agents/__init__.py
dspygen/agents/analytics_agent.py
dspygen/agents/business_logic.py
dspygen/agents/challenger_agent.py
dspygen/agents/coder_agent.py
dspygen/agents/coder_agent_v2.py
dspygen/agents/coder_agent_v3.py
dspygen/agents/coder_agent_v4.py
dspygen/agents/gantt_agents/__init__.py
dspygen/agents/gantt_agents/gantt_agent.py
dspygen/agents/gantt_agents/gantt_main.py
dspygen/agents/gantt_agents/gen-orch-planner.pddl
dspygen/agents/gantt_agents/openapi.yaml
dspygen/agents/gantt_agents/pddl_openapi.py
dspygen/agents/gantt_agents/pddl_planning.py
dspygen/agents/idapr_adapter.py
dspygen/agents/mock_dapr_adapter.py
dspygen/agents/order_payload.py
dspygen/agents/pytest_agent.py
dspygen/agents/research_agent.py
dspygen/agents/swarms/__init__.py
dspygen/agents/swarms/agent.http
dspygen/agents/swarms/db.json
dspygen/agents/swarms/go_high_level_swarm.py
dspygen/agents/swarms/pso.py
dspygen/agents/swarms/self_talk_swarm.py
dspygen/agents/workflow_agent.py
dspygen/api.py
dspygen/app.py
dspygen/async_typer.py
dspygen/books/socratic_tutor/book.toml
dspygen/books/socratic_tutor/src/SUMMARY.md
dspygen/books/socratic_tutor/src/appendices/README.md
dspygen/books/socratic_tutor/src/appendices/further-reading.md
dspygen/books/socratic_tutor/src/appendices/glossary.md
dspygen/books/socratic_tutor/src/architecture/actor-model.md
dspygen/books/socratic_tutor/src/architecture/content-management.md
dspygen/books/socratic_tutor/src/architecture/domain-model.md
dspygen/books/socratic_tutor/src/architecture/event-driven.md
dspygen/books/socratic_tutor/src/architecture/feedback-generation.md
dspygen/books/socratic_tutor/src/architecture/question-generation.md
dspygen/books/socratic_tutor/src/architecture/student-modeling.md
dspygen/books/socratic_tutor/src/best-practices/collaboration.md
dspygen/books/socratic_tutor/src/best-practices/domain-modeling.md
dspygen/books/socratic_tutor/src/best-practices/error-handling.md
dspygen-2024.10.15.dist-info/LICENSE
dspygen-2024.10.15.dist-info/METADATA
dspygen-2024.10.15.dist-info/WHEEL
dspygen-2024.10.15.dist-info/entry_points.txt
dspygen-2024.10.15.dist-info/RECORD
