Metadata-Version: 2.1
Name: dspygen
Version: 2024.10.15
Summary: A Ruby on Rails style framework for the DSPy (Demonstrate, Search, Predict) project for Language Models like GPT, BERT, and LLama.
Home-page: https://github.com/seanchatmangpt/dspygen
Author: Sean Chatman
Author-email: info@chatmangpt.com
Requires-Python: >=3.10,<3.13
Classifier: Programming Language :: Python :: 3
Classifier: Programming Language :: Python :: 3.10
Classifier: Programming Language :: Python :: 3.11
Classifier: Programming Language :: Python :: 3.12
Requires-Dist: anyio (>=4.3.0,<5.0.0)
Requires-Dist: apscheduler (>=3.10.4,<4.0.0)
Requires-Dist: asyncer (==0.0.7)
Requires-Dist: chromadb (>=0.5.0,<0.6.0)
Requires-Dist: clingo (>=5.7.1,<6.0.0)
Requires-Dist: coloredlogs (>=15.0.1)
Requires-Dist: confz (>=2.0.1,<3.0.0)
Requires-Dist: docutils (==0.21)
Requires-Dist: dspy-ai (>=2.5.2,<3.0.0)
Requires-Dist: duckduckgo-search (>=5.3.0,<6.0.0)
Requires-Dist: ebooklib (>=0.18,<0.19)
Requires-Dist: factory-boy (>=3.3.0,<4.0.0)
Requires-Dist: fastapi[all] (>=0.92.0)
Requires-Dist: groq (>=0.4.1,<0.5.0)
Requires-Dist: gspread (>=6.1.2,<7.0.0)
Requires-Dist: gunicorn (>=20.1.0)
Requires-Dist: html2text (>=2024.2.26,<2025.0.0)
Requires-Dist: httpx (>=0.27.0,<0.28.0)
Requires-Dist: icalendar (>=5.0.13,<6.0.0)
Requires-Dist: icontract (>=2.6.6,<3.0.0)
Requires-Dist: ijson (>=3.2.3,<4.0.0)
Requires-Dist: inflection (>=0.5.1,<0.6.0)
Requires-Dist: inject (>=5.2.1,<6.0.0)
Requires-Dist: jinja2 (>=3.1.3,<4.0.0)
Requires-Dist: jinja2-ext (>=0.1,<0.2)
Requires-Dist: jinja2-time (>=0.2.0,<0.3.0)
Requires-Dist: loguru (>=0.7.2,<0.8.0)
Requires-Dist: munch (>=4.0.0,<5.0.0)
Requires-Dist: numpy (<2.0.0)
Requires-Dist: ollama (>=0.3.3,<0.4.0)
Requires-Dist: openai (>=1.12.0,<2.0.0)
Requires-Dist: osascript (>=2020.12.3,<2021.0.0)
Requires-Dist: paho-mqtt (>=2.0.0,<3.0.0)
Requires-Dist: pandasql (>=0.7.3,<0.8.0)
Requires-Dist: pddlpy (>=0.4.4,<0.5.0)
Requires-Dist: playwright (>=1.41.2,<2.0.0)
Requires-Dist: pm4py (>=2.7.11.11,<3.0.0.0)
Requires-Dist: poethepoet (>=0.20.0)
Requires-Dist: prefect (>=2.20.4,<3.0.0)
Requires-Dist: protobuf (>=3.20,<3.21)
Requires-Dist: psutil (>=5.9.8,<6.0.0)
Requires-Dist: py-trees (>=2.2.3,<3.0.0)
Requires-Dist: pydantic (>=1.10.7)
Requires-Dist: pydantic-settings (>=2.2.1,<3.0.0)
Requires-Dist: pygame (>=2.5.2,<3.0.0)
Requires-Dist: pykka (>=4.0.2,<5.0.0)
Requires-Dist: pyobjc (>=10.3.1,<11.0.0)
Requires-Dist: pyobjc-framework-contacts (>=10.3.1,<11.0.0)
Requires-Dist: pyobjc-framework-eventkit (>=10.3.1,<11.0.0)
Requires-Dist: pypdf (>=4.1.0,<5.0.0)
Requires-Dist: pyperclip (>=1.8.2,<2.0.0)
Requires-Dist: pytest-asyncio (>=0.23.5,<0.24.0)
Requires-Dist: pytest-httpx (>=0.30.0,<0.31.0)
Requires-Dist: python-docx (>=1.1.0,<2.0.0)
Requires-Dist: python-dotenv (>=1.0.1,<2.0.0)
Requires-Dist: python-pptx (>=0.6.23,<0.7.0)
Requires-Dist: pytz (>=2024.1,<2025.0)
Requires-Dist: reactivex (>=4.0.4,<5.0.0)
Requires-Dist: realtime (>=2.0.1,<3.0.0)
Requires-Dist: sentify (>=0.7.4,<0.8.0)
Requires-Dist: sqlmodel (>=0.0.16,<0.0.17)
Requires-Dist: st-pages (>=0.4.5,<0.5.0)
Requires-Dist: streamlit (>=1.19.0)
Requires-Dist: sungen (>=2024.9.28,<2025.0.0)
Requires-Dist: tpot (>=0.12.2,<0.13.0)
Requires-Dist: trafilatura (>=1.12.1,<2.0.0)
Requires-Dist: transitions (>=0.9.0,<0.10.0)
Requires-Dist: typer[all] (>=0.9.0)
Requires-Dist: tzlocal (>=5.2,<6.0)
Requires-Dist: uvicorn[standard] (>=0.20.0)
Requires-Dist: websockets (>=12.0,<13.0)
Project-URL: Repository, https://github.com/seanchatmangpt/dspygen
